{
  "animalOfTheDay": {
    "name": "viper",
    "facts": [
      "Their hinged fangs fold against the roof of mouth when not striking.",
      "Vipers have heat-sensing pits detecting temperature changes as small as 0.003°C.",
      "Horned vipers in deserts move via sidewinding to avoid hot sand.",
      "Gaboon vipers have longest fangs (2 inches) and highest venom yield."
    ],
    "images": [
      "https://images.pexels.com/photos/36714/snake-rattlesnake-reptile-skin.jpg?auto=compress&cs=tinysrgb&dpr=2&h=650&w=940",
      "https://images.pexels.com/photos/2581178/pexels-photo-2581178.jpeg?auto=compress&cs=tinysrgb&dpr=2&h=650&w=940"
    ]
  },
  "calendar": [
    {
      "date": "08-12",
      "name": "sloth",
      "facts": [
        "They only come down from the trees about once a week to defecate.",
        "Sloths have a symbiotic relationship with algae, which grows on their fur and provides camouflage.",
        "They spend most of their lives hanging upside down in trees, even sleeping and giving birth in this position.",
        "Sloths are the slowest mammals on Earth, moving at a top speed of about 0.24 km/h."
      ],
      "images": [
        "https://images.pexels.com/photos/2123059/pexels-photo-2123059.jpeg?auto=compress&cs=tinysrgb&dpr=2&h=650&w=940",
        "https://images.pexels.com/photos/4484954/pexels-photo-4484954.jpeg?auto=compress&cs=tinysrgb&dpr=2&h=650&w=940"
      ]
    },
    {
      "date": "08-13",
      "name": "turkey",
      "facts": [
        "Wild turkeys can fly short distances at speeds of up to 55 mph.",
        "Male turkeys, called toms, puff up their feathers and fan their tails to attract females.",
        "Benjamin Franklin once proposed the turkey as the national bird of the United States.",
        "They have excellent vision and can see in color, with a nearly 360-degree field of view."
      ],
      "images": [
        "https://images.pexels.com/photos/2048865/pexels-photo-2048865.jpeg?auto=compress&cs=tinysrgb&dpr=2&h=650&w=940",
        "https://images.pexels.com/photos/917595/pexels-photo-917595.jpeg?auto=compress&cs=tinysrgb&dpr=2&h=650&w=940"
      ]
    },
    {
      "date": "08-14",
      "name": "turtle",
      "facts": [
        "Turtles have been around for over 200 million years, outliving the dinosaurs.",
        "Some turtles, like the leatherback, can dive to depths of over 4,000 feet.",
        "They can breathe through their butts (cloacal respiration) when hibernating underwater.",
        "The gender of many turtle species is determined by the temperature of the nest."
      ],
      "images": [
        "https://images.pexels.com/photos/1618606/pexels-photo-1618606.jpeg?auto=compress&cs=tinysrgb&dpr=2&h=650&w=940",
        "https://images.pexels.com/photos/789141/pexels-photo-789141.jpeg?auto=compress&cs=tinysrgb&dpr=2&h=650&w=940"
      ]
    },
    {
      "date": "08-15",
      "name": "umbrellabird",
      "facts": [
        "Umbrellabirds get their name from the distinctive umbrella-like crest on the male's head.",
        "They are found only in the rainforests of Central and South America.",
        "They have one of the deepest voices in the bird world, producing loud, booming calls.",
        "Males gather in groups called leks to perform courtship displays for females."
      ],
      "images": [
        "https://images.pexels.com/photos/206770/pexels-photo-206770.jpeg?auto=compress&cs=tinysrgb&dpr=2&h=650&w=940",
        "https://images.pexels.com/photos/32568477/pexels-photo-32568477.jpeg?auto=compress&cs=tinysrgb&dpr=2&h=650&w=940"
      ]
    },
    {
      "date": "08-16",
      "name": "vampire bat",
      "facts": [
        "Vampire bats share regurgitated blood with starving colony members – reciprocal altruism.",
        "They use infrared sensors on noses to detect blood vessels.",
        "Bat saliva contains draculin – an anticoagulant studied for stroke treatment.",
        "Vampires run on ground using folded wings as front legs."
      ],
      "images": [
        "https://images.pexels.com/photos/7140769/pexels-photo-7140769.jpeg?auto=compress&cs=tinysrgb&dpr=2&h=650&w=940",
        "https://images.pexels.com/photos/9740381/pexels-photo-9740381.jpeg?auto=compress&cs=tinysrgb&dpr=2&h=650&w=940"
      ]
    },
    {
      "date": "08-17",
      "name": "vicuna",
      "facts": [
        "Vicuñas produce the finest wool – fibers measure 12 micrometers (human hair: 75).",
        "They have lower incisor teeth that grow continuously like rodents.",
        "Inca royalty wore vicuña robes; illegal poaching still threatens populations.",
        "Vicuñas spit foul-smelling cud at competitors during disputes."
      ],
      "images": [
        "https://images.pexels.com/photos/4613387/pexels-photo-4613387.jpeg?auto=compress&cs=tinysrgb&dpr=2&h=650&w=940",
        "https://images.pexels.com/photos/17987435/pexels-photo-17987435.jpeg?auto=compress&cs=tinysrgb&dpr=2&h=650&w=940"
      ]
    },
    {
      "date": "08-18",
      "name": "viper",
      "facts": [
        "Vipers have heat-sensing pits detecting temperature changes as small as 0.003°C.",
        "Their hinged fangs fold against the roof of mouth when not striking.",
        "Gaboon vipers have longest fangs (2 inches) and highest venom yield.",
        "Horned vipers in deserts move via sidewinding to avoid hot sand."
      ],
      "images": [
        "https://images.pexels.com/photos/36714/snake-rattlesnake-reptile-skin.jpg?auto=compress&cs=tinysrgb&dpr=2&h=650&w=940",
        "https://images.pexels.com/photos/2581178/pexels-photo-2581178.jpeg?auto=compress&cs=tinysrgb&dpr=2&h=650&w=940"
      ]
    }
  ],
  "randomAnimals": [
    {
      "name": "hornbill",
      "facts": [
        "Hornbills play a vital role in seed dispersal in tropical forests.",
        "They seal the entrance of their nests with mud, leaving only a small slit to pass food.",
        "Some species perform elaborate courtship dances, including bowing and bill-clapping.",
        "Hornbills are known for their large, curved beaks, which are often brightly colored."
      ],
      "images": [
        "https://images.pexels.com/photos/55746/hornbill-bird-tropical-zoo-55746.jpeg?auto=compress&cs=tinysrgb&dpr=2&h=650&w=940",
        "https://images.pexels.com/photos/312838/pexels-photo-312838.jpeg?auto=compress&cs=tinysrgb&dpr=2&h=650&w=940"
      ]
    },
    {
      "name": "ocelot",
      "facts": [
        "Ocelots are beautiful wild cats from Central and South America, known for their distinctive, spotted fur resembling a leopard.",
        "They are nocturnal animals that spend most of their time in trees, where they hunt birds and small mammals.",
        "They have incredibly keen eyesight, allowing them to see in very low light.",
        "Each ocelot has a unique pattern of spots, which allows for identification."
      ],
      "images": [
        "https://images.pexels.com/photos/20831801/pexels-photo-20831801.jpeg?auto=compress&cs=tinysrgb&dpr=2&h=650&w=940",
        "https://images.pexels.com/photos/28517671/pexels-photo-28517671.jpeg?auto=compress&cs=tinysrgb&dpr=2&h=650&w=940"
      ]
    },
    {
      "name": "jerboa",
      "facts": [
        "They have a very long tail that helps them maintain balance during jumps.",
        "They can jump up to 3 meters (10 feet) high and 6 meters (20 feet) long to escape predators.",
        "They are nocturnal animals that spend the day in cool burrows to avoid the heat.",
        "Jerboas are small rodents from the deserts of Africa and Asia, known for their long hind legs and ability to jump long distances."
      ],
      "images": [
        "https://images.pexels.com/photos/735431/pexels-photo-735431.jpeg?auto=compress&cs=tinysrgb&dpr=2&h=650&w=940",
        "https://images.pexels.com/photos/7723964/pexels-photo-7723964.jpeg?auto=compress&cs=tinysrgb&dpr=2&h=650&w=940"
      ]
    }
  ]
}